liferaft_python_lib/__init__.py
liferaft_python_lib/logger.py
liferaft_python_lib/main.py
liferaft_python_lib/test.py
liferaft_python_lib/abcs/queue_adapter_abc.py
liferaft_python_lib/adapters/beanstalk_adapter.py
liferaft_python_lib/adapters/rabbitmq_adapter.py
liferaft_python_lib/settings/benstalk_adapter_settings.py
liferaft_python_lib/settings/config_dict.py
liferaft_python_lib/settings/rabbitmq_adapter_settings.py
liferaft_python_lib-0.0.5.dist-info/LICENSE
liferaft_python_lib-0.0.5.dist-info/METADATA
liferaft_python_lib-0.0.5.dist-info/WHEEL
liferaft_python_lib-0.0.5.dist-info/top_level.txt
liferaft_python_lib-0.0.5.dist-info/RECORD
