Metadata-Version: 2.1
Name: liferaft-python-lib
Version: 0.0.5
Summary: A shared library for reusable abstracted components
Home-page: UNKNOWN
Author: ORION
Author-email: orion@liferaftinc.com
License: MIT
Platform: UNKNOWN
Classifier: Programming Language :: Python :: 3.9
Classifier: License :: OSI Approved :: MIT License
Classifier: Operating System :: OS Independent
Requires-Python: >=3.9
License-File: LICENSE
Requires-Dist: pika>=1.3.0
Requires-Dist: pydantic>=2.0.3
Requires-Dist: tenacity>=8.3.0
Requires-Dist: pyyaml>=5.4
